[
  {
    "content_id": 800194,
    "reference_id": 26829,
    "title": "Informações de fundo",
    "media_type": "Text",
    "index_reference": "informações de fundo",
    "language": "por",
    "content": "<h3>Descrição</h3><p>Quando as pessoas contam uma história, elas normalmente narram os eventos na ordem em que aconteceram. Essa sequência de eventos compõe a trama. A trama está cheia de verbos de ação que fazem a história avançar no tempo. No entanto, às vezes, um escritor pode fazer uma pausa na trama e fornecer algumas informações para ajudar seus ouvintes a entenderem melhor a história. Esse tipo de informação é chamado de informação de fundo. As informações de fundo podem ser sobre coisas que aconteceram antes dos eventos já contados, podem explicar algo na história ou podem ser sobre algo que aconteceria muito mais tarde na história.</p><p><strong>Exemplo</strong> — As frases em negrito na história abaixo são todas informações fundo.</p><p>Pedro e João foram em uma viagem de caça porque <strong>sua aldeia teria uma festa no dia seguinte</strong>. <strong>Pedro era o melhor caçador da aldeia.</strong> <strong>Ele uma vez matou três javalis em um único dia!</strong> Eles caminharam por horas através de arbustos baixos até ouvirem um javali. O javali correu, mas eles conseguiram atirar nele e matá-lo. Então amarraram suas pernas com uma corda <strong>que tinham trazido com eles</strong> e o carregaram para casa em um mastro. Quando o levaram para a aldeia, o primo de Pedro viu o javali e percebeu que era seu próprio porco. Pedro tinha matado por engano o porco de seu primo.</p><p>Informações de fundo frequentemente falam sobre algo que aconteceu anteriormente ou algo que aconteceria muito mais tarde. Exemplos disso são: “a aldeia deles teria uma festa no dia seguinte”, “Ele uma vez matou três porcos selvagens em um dia” e “que eles tinham trazido com eles”.</p><p>Frequentemente, informações de fundo usam verbos como &quot;ser&quot;, como &quot;era&quot; e &quot;estavam&quot;, em vez de verbos de ação. Exemplos disso são &quot;a aldeia deles teria uma festa no dia seguinte&quot; e &quot;Pedro <strong>era</strong> o melhor caçador da aldeia&quot;.</p><p>Informações de fundo também podem ser destacadas com palavras que indicam ao leitor que essas informações não fazem parte da sequência de eventos da história. Nesta história, algumas dessas palavras são &quot;porque&quot;, &quot;uma vez&quot; e &quot;tinha&quot;.</p><h1>Um escritor pode usar informações de fundo:</h1><ul><li><p>para ajudar seus ouvintes a se interessarem pela narrativa</p></li><li><p>para ajudar seus ouvintes a compreenderem algo na história</p></li><li><p>para ajudar os ouvintes a entenderem por que algo é importante na história</p></li><li><p>para descrever o cenário de uma história</p></li></ul><ul><li><p>A configuração inclui:</p></li><li><p>onde a história se desenrola</p></li><li><p>quando a história ocorre</p></li><li><p>Quem está presente quando a história começa?</p></li><li><p>O que está acontecendo quando a história começa?</p></li></ul><h1>Razões pelas quais isso é um problema de tradução</h1><ul><li><p>As línguas têm diferentes maneiras de marcar informações de fundo e informações da trama.</p></li><li><p>Você (o tradutor) precisa saber a ordem dos eventos na Bíblia, quais informações são de fundo e quais fazem parte da história.</p></li><li><p>Você precisará traduzir a história de uma maneira que destaque as informações de fundo, para que seus leitores compreendam a ordem dos eventos, quais informações são de fundo e quais pertencem à linha principal da história.</p></li></ul><h3>Exemplos da Bíblia</h3><p>Hagar deu à luz o filho de Abrão, e Abrão chamou seu filho, que Hagar gerou, de Ismael. Abrão <strong>tinha 86 anos</strong> quando Hagar deu à luz Ismael para Abrão. (Gênesis 16.15–16)</p><p>A primeira frase menciona dois eventos: Hagar deu à luz e Abraão nomeou seu filho. A segunda frase fornece informações de fundo sobre a idade de Abrão quando esses eventos ocorreram.</p><p>O próprio Jesus <strong>tinha cerca de 30 anos</strong>. Ele <strong>era filho</strong> (como se pensava) de José, de Eli, (Lucas 3.23)</p><p>Os versículos anteriores falam sobre o batismo de Jesus. Esta frase introduz informações de fundo sobre a idade e os ancestrais de Jesus. A história continua no capítulo 4, onde é mencionado que Jesus vai para o deserto.</p><p>Então <strong>aconteceu em um sábado</strong> que ele <strong>estava passando pelos campos de grãos</strong>, e seus discípulos <strong>colhiam e comiam as espigas de grãos</strong>, <strong>esfregando-as nas mãos</strong>. Mas alguns dos fariseus disseram... (Lucas 6.1–2a)</p><p>Esses versículos estabelecem o cenário da história. Os eventos ocorreram em um campo de grãos no sábado. Jesus, seus discípulos e alguns fariseus estavam presentes, e os discípulos de Jesus estavam colhendo espigas de grãos e comendo-as. A ação principal da história começa com a frase: &quot;Mas alguns dos fariseus disseram...&quot;.</p><h3>Estratégias de tradução</h3><p>Para manter as traduções claras e naturais, você precisará estudar como as pessoas contam histórias em seu idioma. Observe como seu idioma marca as informações de fundo. Pode ser necessário anotar algumas histórias para estudar isso. Observe que tipos de verbos seu idioma usa para informações de fundo e que tipos de palavras ou outros marcadores sinalizam que algo é informação de fundo. Faça essas mesmas coisas ao traduzir, para que sua tradução seja clara e natural e as pessoas possam entendê-la facilmente.</p><p>(1) Utilize a forma do seu idioma para indicar que certas informações são de fundo. (2) Reorganize as informações para que eventos anteriores sejam mencionados primeiro. (Isso nem sempre é possível quando as informações de fundo são muito extensas.)</p><h3>Exemplos de estratégias aplicadas na tradução</h3><p>(1) Utilize a forma do seu idioma para indicar que certas informações são de contexto. Os exemplos abaixo explicam como isso foi feito em algumas traduções.</p><p><strong>E</strong> o próprio Jesus <strong>tinha</strong> cerca de 30 anos. Ele <strong>era</strong> filho (como se supunha) de José, filho de Eli. (Lucas 3.23)</p><p>Assim como aqui, o português às vezes usa a palavra &quot;e&quot; para indicar que há algum tipo de mudança na história. O verbo &quot;era&quot; indica que são informações de fundo.</p><p>Portanto, ao exortar sobre muitas outras coisas, ele anunciava as boas-novas ao povo. Mas Herodes, o tetrarca, tendo sido repreendido por ele a respeito de Herodias, a esposa de seu irmão, e <strong>sobre todas as coisas más que Herodes havia feito</strong>, acrescentou ainda isto a todas elas: Ele prendeu João. (Lucas 3.18–20)</p><p>A frase em negrito ocorreu antes de João repreender Herodes. Em português, o verbo auxiliar “havia” em “havia feito” indica que Herodes fez essas coisas antes de João repreendê-lo.</p><p>(2) Reorganize as informações para que os eventos anteriores sejam mencionados primeiro.</p><p>Agar deu à luz o filho de Abrão, e Abrão chamou seu filho, que Agar lhe deu, de Ismael. <strong>Abrão tinha 86 anos quando Agar deu Ismael a Abrão</strong>. (Gênesis 16.16)</p><p>“<strong>Quando Abrão tinha 86 anos</strong>, Hagar deu à luz seu filho, e Abrão o chamou de Ismael”.</p><p>Portanto, ao exortar sobre muitas outras coisas, ele anunciava as boas-novas ao povo. Mas Herodes, o tetrarca, tendo sido repreendido por ele a respeito de Herodias, a esposa de seu irmão, e <strong>sobre todas as coisas más que Herodes havia feito</strong>, acrescentou ainda isto a todas elas: Ele prendeu João na prisão. (Lucas 3.18–20)</p><p>A tradução abaixo reorganiza a repreensão de João e as ações de Herodes de forma mais clara.</p><p>“Herodes, o tetrarca, casou-se com Herodias, esposa de seu irmão, e <strong>cometeu muitas outras maldades</strong>, então João o repreendeu. Mas Herodes fez algo ainda pior. Ele mandou prender João na prisão”.</p><p>*Os textos bíblicos desta seção são uma tradução literal livre — a menos que indicado diretamente que se trata de uma versão&nbsp;específica.</p>",
    "associations": {
      "passage": [],
      "resource": [
        {
          "reference_id": 115758,
          "content_id": 234487,
          "resource_code": "Unknown",
          "label": "Marcos 1.6 (#1)",
          "language": "por"
        },
        {
          "reference_id": 115807,
          "content_id": 234536,
          "resource_code": "Unknown",
          "label": "Marcos 1.16 (#6)",
          "language": "por"
        },
        {
          "reference_id": 115858,
          "content_id": 234587,
          "resource_code": "Unknown",
          "label": "Marcos 1.30 (#1)",
          "language": "por"
        },
        {
          "reference_id": 115996,
          "content_id": 234725,
          "resource_code": "Unknown",
          "label": "Marcos 2.18 (#2)",
          "language": "por"
        },
        {
          "reference_id": 116102,
          "content_id": 234831,
          "resource_code": "Unknown",
          "label": "Marcos 3.19 (#1)",
          "language": "por"
        },
        {
          "reference_id": 116377,
          "content_id": 235106,
          "resource_code": "Unknown",
          "label": "Marcos 5.3 (#1)",
          "language": "por"
        },
        {
          "reference_id": 116401,
          "content_id": 235130,
          "resource_code": "Unknown",
          "label": "Marcos 5.11 (#1)",
          "language": "por"
        },
        {
          "reference_id": 116460,
          "content_id": 235189,
          "resource_code": "Unknown",
          "label": "Marcos 5.26 (#1)",
          "language": "por"
        },
        {
          "reference_id": 116729,
          "content_id": 235458,
          "resource_code": "Unknown",
          "label": "Marcos 6.44 (#1)",
          "language": "por"
        },
        {
          "reference_id": 116794,
          "content_id": 235523,
          "resource_code": "Unknown",
          "label": "Marcos 7.3 (#1)",
          "language": "por"
        },
        {
          "reference_id": 116922,
          "content_id": 235651,
          "resource_code": "Unknown",
          "label": "Marcos 7.26 (#1)",
          "language": "por"
        },
        {
          "reference_id": 117000,
          "content_id": 235729,
          "resource_code": "Unknown",
          "label": "Marcos 8.9 (#1)",
          "language": "por"
        },
        {
          "reference_id": 117025,
          "content_id": 235754,
          "resource_code": "Unknown",
          "label": "Marcos 8.14 (#1)",
          "language": "por"
        },
        {
          "reference_id": 117173,
          "content_id": 235902,
          "resource_code": "Unknown",
          "label": "Marcos 9.6 (#1)",
          "language": "por"
        },
        {
          "reference_id": 117876,
          "content_id": 236605,
          "resource_code": "Unknown",
          "label": "Marcos 12.18 (#2)",
          "language": "por"
        },
        {
          "reference_id": 118260,
          "content_id": 236989,
          "resource_code": "Unknown",
          "label": "Marcos 14.1 (#1)",
          "language": "por"
        },
        {
          "reference_id": 118470,
          "content_id": 237199,
          "resource_code": "Unknown",
          "label": "Marcos 14.44 (#1)",
          "language": "por"
        },
        {
          "reference_id": 118614,
          "content_id": 237343,
          "resource_code": "Unknown",
          "label": "Marcos 15.6 (#1)",
          "language": "por"
        },
        {
          "reference_id": 118618,
          "content_id": 237347,
          "resource_code": "Unknown",
          "label": "Marcos 15.7 (#1)",
          "language": "por"
        },
        {
          "reference_id": 118682,
          "content_id": 237411,
          "resource_code": "Unknown",
          "label": "Marcos 15.21 (#5)",
          "language": "por"
        },
        {
          "reference_id": 118696,
          "content_id": 237425,
          "resource_code": "Unknown",
          "label": "Marcos 15.25 (#1)",
          "language": "por"
        },
        {
          "reference_id": 118751,
          "content_id": 237480,
          "resource_code": "Unknown",
          "label": "Marcos 15.40 (#1)",
          "language": "por"
        },
        {
          "reference_id": 118757,
          "content_id": 237486,
          "resource_code": "Unknown",
          "label": "Marcos 15.41 (#1)",
          "language": "por"
        },
        {
          "reference_id": 118766,
          "content_id": 237495,
          "resource_code": "Unknown",
          "label": "Marcos 15.43 (#3)",
          "language": "por"
        },
        {
          "reference_id": 136716,
          "content_id": 309807,
          "resource_code": "Unknown",
          "label": "Atos 1.15 (#6)",
          "language": "por"
        },
        {
          "reference_id": 136732,
          "content_id": 309823,
          "resource_code": "Unknown",
          "label": "Atos 1.18 (#1)",
          "language": "por"
        },
        {
          "reference_id": 137030,
          "content_id": 310121,
          "resource_code": "Unknown",
          "label": "Atos 3.2 (#2)",
          "language": "por"
        },
        {
          "reference_id": 137222,
          "content_id": 310313,
          "resource_code": "Unknown",
          "label": "Atos 4.22 (#1)",
          "language": "por"
        },
        {
          "reference_id": 137436,
          "content_id": 310527,
          "resource_code": "Unknown",
          "label": "Atos 5.34 (#3)",
          "language": "por"
        },
        {
          "reference_id": 137797,
          "content_id": 310888,
          "resource_code": "Unknown",
          "label": "Atos 8.1 (#1)",
          "language": "por"
        },
        {
          "reference_id": 140244,
          "content_id": 307210,
          "resource_code": "Unknown",
          "label": "João 1.24 (#1)",
          "language": "por"
        },
        {
          "reference_id": 140254,
          "content_id": 307220,
          "resource_code": "Unknown",
          "label": "João 1.28 (#1)",
          "language": "por"
        },
        {
          "reference_id": 140311,
          "content_id": 307277,
          "resource_code": "Unknown",
          "label": "João 1.44 (#1)",
          "language": "por"
        },
        {
          "reference_id": 140335,
          "content_id": 307301,
          "resource_code": "Unknown",
          "label": "João 2.1 (#1)",
          "language": "por"
        },
        {
          "reference_id": 140354,
          "content_id": 307320,
          "resource_code": "Unknown",
          "label": "João 2.9 (#2)",
          "language": "por"
        },
        {
          "reference_id": 140359,
          "content_id": 307325,
          "resource_code": "Unknown",
          "label": "João 2.11 (#1)",
          "language": "por"
        },
        {
          "reference_id": 140543,
          "content_id": 307509,
          "resource_code": "Unknown",
          "label": "João 4.1 (#1)",
          "language": "por"
        },
        {
          "reference_id": 140687,
          "content_id": 307653,
          "resource_code": "Unknown",
          "label": "João 5.1 (#1)",
          "language": "por"
        },
        {
          "reference_id": 140702,
          "content_id": 307668,
          "resource_code": "Unknown",
          "label": "João 5.9 (#1)",
          "language": "por"
        },
        {
          "reference_id": 140720,
          "content_id": 307686,
          "resource_code": "Unknown",
          "label": "João 5.16 (#1)",
          "language": "por"
        },
        {
          "reference_id": 140826,
          "content_id": 307792,
          "resource_code": "Unknown",
          "label": "João 6.1-4 (#1)",
          "language": "por"
        },
        {
          "reference_id": 140831,
          "content_id": 307797,
          "resource_code": "Unknown",
          "label": "João 6.4 (#1)",
          "language": "por"
        },
        {
          "reference_id": 140836,
          "content_id": 307802,
          "resource_code": "Unknown",
          "label": "João 6.6 (#1)",
          "language": "por"
        },
        {
          "reference_id": 140848,
          "content_id": 307814,
          "resource_code": "Unknown",
          "label": "João 6.10 (#4)",
          "language": "por"
        },
        {
          "reference_id": 140866,
          "content_id": 307832,
          "resource_code": "Unknown",
          "label": "João 6.17 (#1)",
          "language": "por"
        },
        {
          "reference_id": 140878,
          "content_id": 307844,
          "resource_code": "Unknown",
          "label": "João 6.23 (#1)",
          "language": "por"
        },
        {
          "reference_id": 137828,
          "content_id": 310919,
          "resource_code": "Unknown",
          "label": "Atos 8.9 (#1)",
          "language": "por"
        },
        {
          "reference_id": 137838,
          "content_id": 310929,
          "resource_code": "Unknown",
          "label": "Atos 8.11 (#1)",
          "language": "por"
        },
        {
          "reference_id": 137897,
          "content_id": 310988,
          "resource_code": "Unknown",
          "label": "Atos 8.26 (#4)",
          "language": "por"
        },
        {
          "reference_id": 137900,
          "content_id": 310991,
          "resource_code": "Unknown",
          "label": "Atos 8.27 (#3)",
          "language": "por"
        },
        {
          "reference_id": 138057,
          "content_id": 311148,
          "resource_code": "Unknown",
          "label": "Atos 9.33 (#4)",
          "language": "por"
        },
        {
          "reference_id": 138446,
          "content_id": 311537,
          "resource_code": "Unknown",
          "label": "Atos 13.7 (#3)",
          "language": "por"
        },
        {
          "reference_id": 138473,
          "content_id": 311564,
          "resource_code": "Unknown",
          "label": "Atos 13.13 (#2)",
          "language": "por"
        },
        {
          "reference_id": 139005,
          "content_id": 312096,
          "resource_code": "Unknown",
          "label": "Atos 17.11 (#1)",
          "language": "por"
        },
        {
          "reference_id": 139040,
          "content_id": 312131,
          "resource_code": "Unknown",
          "label": "Atos 17.21 (#1)",
          "language": "por"
        },
        {
          "reference_id": 139169,
          "content_id": 312260,
          "resource_code": "Unknown",
          "label": "Atos 18.24 (#1)",
          "language": "por"
        },
        {
          "reference_id": 139228,
          "content_id": 312319,
          "resource_code": "Unknown",
          "label": "Atos 19.14 (#1)",
          "language": "por"
        },
        {
          "reference_id": 139259,
          "content_id": 312350,
          "resource_code": "Unknown",
          "label": "Atos 19.24 (#3)",
          "language": "por"
        },
        {
          "reference_id": 139462,
          "content_id": 312553,
          "resource_code": "Unknown",
          "label": "Atos 21.9 (#1)",
          "language": "por"
        },
        {
          "reference_id": 139687,
          "content_id": 312778,
          "resource_code": "Unknown",
          "label": "Atos 23.8 (#1)",
          "language": "por"
        },
        {
          "reference_id": 140031,
          "content_id": 313122,
          "resource_code": "Unknown",
          "label": "Atos 27.37 (#1)",
          "language": "por"
        },
        {
          "reference_id": 140056,
          "content_id": 313147,
          "resource_code": "Unknown",
          "label": "Atos 28.7 (#1)",
          "language": "por"
        },
        {
          "reference_id": 142779,
          "content_id": 302702,
          "resource_code": "Unknown",
          "label": "Lucas 1.3 (#1)",
          "language": "por"
        },
        {
          "reference_id": 142803,
          "content_id": 302726,
          "resource_code": "Unknown",
          "label": "Lucas 1.8 (#5)",
          "language": "por"
        },
        {
          "reference_id": 142804,
          "content_id": 302727,
          "resource_code": "Unknown",
          "label": "Lucas 1.9 (#1)",
          "language": "por"
        },
        {
          "reference_id": 142873,
          "content_id": 302796,
          "resource_code": "Unknown",
          "label": "Lucas 1.27 (#3)",
          "language": "por"
        },
        {
          "reference_id": 143064,
          "content_id": 302987,
          "resource_code": "Unknown",
          "label": "Lucas 2.3 (#1)",
          "language": "por"
        },
        {
          "reference_id": 143086,
          "content_id": 303009,
          "resource_code": "Unknown",
          "label": "Lucas 2.8 (#1)",
          "language": "por"
        },
        {
          "reference_id": 143309,
          "content_id": 303232,
          "resource_code": "Unknown",
          "label": "Lucas 3.19 (#1)",
          "language": "por"
        },
        {
          "reference_id": 143322,
          "content_id": 303245,
          "resource_code": "Unknown",
          "label": "Lucas 3.23 (#1)",
          "language": "por"
        },
        {
          "reference_id": 143813,
          "content_id": 303736,
          "resource_code": "Unknown",
          "label": "Lucas 7.12 (#1)",
          "language": "por"
        },
        {
          "reference_id": 143818,
          "content_id": 303741,
          "resource_code": "Unknown",
          "label": "Lucas 7.12 (#6)",
          "language": "por"
        },
        {
          "reference_id": 144061,
          "content_id": 303984,
          "resource_code": "Unknown",
          "label": "Lucas 8.27 (#4)",
          "language": "por"
        },
        {
          "reference_id": 144072,
          "content_id": 303995,
          "resource_code": "Unknown",
          "label": "Lucas 8.29 (#3)",
          "language": "por"
        },
        {
          "reference_id": 144080,
          "content_id": 304003,
          "resource_code": "Unknown",
          "label": "Lucas 8.32 (#1)",
          "language": "por"
        },
        {
          "reference_id": 144119,
          "content_id": 304042,
          "resource_code": "Unknown",
          "label": "Lucas 8.42 (#3)",
          "language": "por"
        },
        {
          "reference_id": 144181,
          "content_id": 304104,
          "resource_code": "Unknown",
          "label": "Lucas 9.7 (#1)",
          "language": "por"
        },
        {
          "reference_id": 141015,
          "content_id": 307981,
          "resource_code": "Unknown",
          "label": "João 6.59 (#1)",
          "language": "por"
        },
        {
          "reference_id": 141035,
          "content_id": 308001,
          "resource_code": "Unknown",
          "label": "João 6.64 (#1)",
          "language": "por"
        },
        {
          "reference_id": 141056,
          "content_id": 308022,
          "resource_code": "Unknown",
          "label": "João 6.71 (#1)",
          "language": "por"
        },
        {
          "reference_id": 141061,
          "content_id": 308027,
          "resource_code": "Unknown",
          "label": "João 7.2 (#1)",
          "language": "por"
        },
        {
          "reference_id": 141069,
          "content_id": 308035,
          "resource_code": "Unknown",
          "label": "João 7.5 (#1)",
          "language": "por"
        },
        {
          "reference_id": 141113,
          "content_id": 308079,
          "resource_code": "Unknown",
          "label": "João 7.22 (#2)",
          "language": "por"
        },
        {
          "reference_id": 141171,
          "content_id": 308137,
          "resource_code": "Unknown",
          "label": "João 7.39 (#1)",
          "language": "por"
        },
        {
          "reference_id": 141192,
          "content_id": 308158,
          "resource_code": "Unknown",
          "label": "João 7.50 (#1)",
          "language": "por"
        },
        {
          "reference_id": 141230,
          "content_id": 308196,
          "resource_code": "Unknown",
          "label": "João 8.20 (#1)",
          "language": "por"
        },
        {
          "reference_id": 141258,
          "content_id": 308224,
          "resource_code": "Unknown",
          "label": "João 8.27 (#1)",
          "language": "por"
        },
        {
          "reference_id": 141374,
          "content_id": 308340,
          "resource_code": "Unknown",
          "label": "João 9.7 (#4)",
          "language": "por"
        },
        {
          "reference_id": 141387,
          "content_id": 308353,
          "resource_code": "Unknown",
          "label": "João 9.14 (#1)",
          "language": "por"
        },
        {
          "reference_id": 141407,
          "content_id": 308373,
          "resource_code": "Unknown",
          "label": "João 9.22 (#1)",
          "language": "por"
        },
        {
          "reference_id": 141532,
          "content_id": 308498,
          "resource_code": "Unknown",
          "label": "João 10.22 (#1)",
          "language": "por"
        },
        {
          "reference_id": 141593,
          "content_id": 308559,
          "resource_code": "Unknown",
          "label": "João 11.1 (#1)",
          "language": "por"
        },
        {
          "reference_id": 141608,
          "content_id": 308574,
          "resource_code": "Unknown",
          "label": "João 11.5 (#1)",
          "language": "por"
        },
        {
          "reference_id": 141621,
          "content_id": 308587,
          "resource_code": "Unknown",
          "label": "João 11.13 (#1)",
          "language": "por"
        },
        {
          "reference_id": 141630,
          "content_id": 308596,
          "resource_code": "Unknown",
          "label": "João 11.18 (#1)",
          "language": "por"
        },
        {
          "reference_id": 141632,
          "content_id": 308598,
          "resource_code": "Unknown",
          "label": "João 11.19 (#1)",
          "language": "por"
        },
        {
          "reference_id": 141657,
          "content_id": 308623,
          "resource_code": "Unknown",
          "label": "João 11.30 (#1)",
          "language": "por"
        },
        {
          "reference_id": 141673,
          "content_id": 308639,
          "resource_code": "Unknown",
          "label": "João 11.38 (#2)",
          "language": "por"
        },
        {
          "reference_id": 141703,
          "content_id": 308669,
          "resource_code": "Unknown",
          "label": "João 11.51-52 (#1)",
          "language": "por"
        },
        {
          "reference_id": 141738,
          "content_id": 308704,
          "resource_code": "Unknown",
          "label": "João 12.6 (#1)",
          "language": "por"
        },
        {
          "reference_id": 141750,
          "content_id": 308716,
          "resource_code": "Unknown",
          "label": "João 12.9 (#1)",
          "language": "por"
        },
        {
          "reference_id": 141769,
          "content_id": 308735,
          "resource_code": "Unknown",
          "label": "João 12.14 (#1)",
          "language": "por"
        },
        {
          "reference_id": 141833,
          "content_id": 308799,
          "resource_code": "Unknown",
          "label": "João 12.33 (#1)",
          "language": "por"
        },
        {
          "reference_id": 141847,
          "content_id": 308813,
          "resource_code": "Unknown",
          "label": "João 12.37-43 (#1)",
          "language": "por"
        },
        {
          "reference_id": 141894,
          "content_id": 308860,
          "resource_code": "Unknown",
          "label": "João 13.1-4 (#1)",
          "language": "por"
        },
        {
          "reference_id": 141923,
          "content_id": 308889,
          "resource_code": "Unknown",
          "label": "João 13.11 (#1)",
          "language": "por"
        },
        {
          "reference_id": 141962,
          "content_id": 308928,
          "resource_code": "Unknown",
          "label": "João 13.28 (#1)",
          "language": "por"
        },
        {
          "reference_id": 141967,
          "content_id": 308933,
          "resource_code": "Unknown",
          "label": "João 13.30 (#1)",
          "language": "por"
        },
        {
          "reference_id": 142334,
          "content_id": 309300,
          "resource_code": "Unknown",
          "label": "João 18.1-2 (#1)",
          "language": "por"
        },
        {
          "reference_id": 142345,
          "content_id": 309311,
          "resource_code": "Unknown",
          "label": "João 18.5 (#4)",
          "language": "por"
        },
        {
          "reference_id": 142350,
          "content_id": 309316,
          "resource_code": "Unknown",
          "label": "João 18.9 (#1)",
          "language": "por"
        },
        {
          "reference_id": 142362,
          "content_id": 309328,
          "resource_code": "Unknown",
          "label": "João 18.14 (#1)",
          "language": "por"
        },
        {
          "reference_id": 142373,
          "content_id": 309339,
          "resource_code": "Unknown",
          "label": "João 18.18 (#1)",
          "language": "por"
        },
        {
          "reference_id": 142400,
          "content_id": 309366,
          "resource_code": "Unknown",
          "label": "João 18.28 (#5)",
          "language": "por"
        },
        {
          "reference_id": 142410,
          "content_id": 309376,
          "resource_code": "Unknown",
          "label": "João 18.32 (#1)",
          "language": "por"
        },
        {
          "reference_id": 142439,
          "content_id": 309405,
          "resource_code": "Unknown",
          "label": "João 18.40 (#4)",
          "language": "por"
        },
        {
          "reference_id": 142482,
          "content_id": 309448,
          "resource_code": "Unknown",
          "label": "João 19.14 (#1)",
          "language": "por"
        },
        {
          "reference_id": 142511,
          "content_id": 309477,
          "resource_code": "Unknown",
          "label": "João 19.23 (#2)",
          "language": "por"
        },
        {
          "reference_id": 142550,
          "content_id": 309516,
          "resource_code": "Unknown",
          "label": "João 19.35 (#1)",
          "language": "por"
        },
        {
          "reference_id": 142553,
          "content_id": 309519,
          "resource_code": "Unknown",
          "label": "João 19.36-37 (#1)",
          "language": "por"
        },
        {
          "reference_id": 142574,
          "content_id": 309540,
          "resource_code": "Unknown",
          "label": "João 19.41 (#1)",
          "language": "por"
        },
        {
          "reference_id": 142612,
          "content_id": 309578,
          "resource_code": "Unknown",
          "label": "João 20.9 (#1)",
          "language": "por"
        },
        {
          "reference_id": 142692,
          "content_id": 309658,
          "resource_code": "Unknown",
          "label": "João 21.2-3 (#1)",
          "language": "por"
        },
        {
          "reference_id": 142708,
          "content_id": 309674,
          "resource_code": "Unknown",
          "label": "João 21.7 (#4)",
          "language": "por"
        },
        {
          "reference_id": 142710,
          "content_id": 309676,
          "resource_code": "Unknown",
          "label": "João 21.8 (#1)",
          "language": "por"
        },
        {
          "reference_id": 142742,
          "content_id": 309708,
          "resource_code": "Unknown",
          "label": "João 21.19 (#1)",
          "language": "por"
        },
        {
          "reference_id": 147380,
          "content_id": 297609,
          "resource_code": "Unknown",
          "label": "Mateus 3.4 (#1)",
          "language": "por"
        },
        {
          "reference_id": 148332,
          "content_id": 298561,
          "resource_code": "Unknown",
          "label": "Mateus 8.28 (#5)",
          "language": "por"
        },
        {
          "reference_id": 148343,
          "content_id": 298572,
          "resource_code": "Unknown",
          "label": "Mateus 8.30 (#1)",
          "language": "por"
        },
        {
          "reference_id": 148569,
          "content_id": 298798,
          "resource_code": "Unknown",
          "label": "Mateus 10.2 (#1)",
          "language": "por"
        },
        {
          "reference_id": 149520,
          "content_id": 299749,
          "resource_code": "Unknown",
          "label": "Mateus 14.3 (#1)",
          "language": "por"
        },
        {
          "reference_id": 149602,
          "content_id": 299831,
          "resource_code": "Unknown",
          "label": "Mateus 14.21 (#1)",
          "language": "por"
        },
        {
          "reference_id": 149849,
          "content_id": 300078,
          "resource_code": "Unknown",
          "label": "Mateus 15.38 (#1)",
          "language": "por"
        },
        {
          "reference_id": 151011,
          "content_id": 301240,
          "resource_code": "Unknown",
          "label": "Mateus 22.23 (#3)",
          "language": "por"
        },
        {
          "reference_id": 151557,
          "content_id": 301786,
          "resource_code": "Unknown",
          "label": "Mateus 25.2 (#1)",
          "language": "por"
        },
        {
          "reference_id": 151963,
          "content_id": 302192,
          "resource_code": "Unknown",
          "label": "Mateus 26.48 (#1)",
          "language": "por"
        },
        {
          "reference_id": 152147,
          "content_id": 302376,
          "resource_code": "Unknown",
          "label": "Mateus 27.15 (#1)",
          "language": "por"
        },
        {
          "reference_id": 152150,
          "content_id": 302379,
          "resource_code": "Unknown",
          "label": "Mateus 27.16 (#1)",
          "language": "por"
        },
        {
          "reference_id": 152312,
          "content_id": 302541,
          "resource_code": "Unknown",
          "label": "Mateus 27.55 (#1)",
          "language": "por"
        },
        {
          "reference_id": 152378,
          "content_id": 302607,
          "resource_code": "Unknown",
          "label": "Mateus 28.3 (#1)",
          "language": "por"
        },
        {
          "reference_id": 144198,
          "content_id": 304121,
          "resource_code": "Unknown",
          "label": "Lucas 9.12 (#1)",
          "language": "por"
        },
        {
          "reference_id": 144258,
          "content_id": 304181,
          "resource_code": "Unknown",
          "label": "Lucas 9.32 (#1)",
          "language": "por"
        },
        {
          "reference_id": 145045,
          "content_id": 304968,
          "resource_code": "Unknown",
          "label": "Lucas 13.6 (#5)",
          "language": "por"
        },
        {
          "reference_id": 145194,
          "content_id": 305117,
          "resource_code": "Unknown",
          "label": "Lucas 14.2 (#4)",
          "language": "por"
        },
        {
          "reference_id": 145659,
          "content_id": 305582,
          "resource_code": "Unknown",
          "label": "Lucas 17.11 (#3)",
          "language": "por"
        },
        {
          "reference_id": 145674,
          "content_id": 305597,
          "resource_code": "Unknown",
          "label": "Lucas 17.16 (#2)",
          "language": "por"
        },
        {
          "reference_id": 145779,
          "content_id": 305702,
          "resource_code": "Unknown",
          "label": "Lucas 18.2 (#3)",
          "language": "por"
        },
        {
          "reference_id": 145816,
          "content_id": 305739,
          "resource_code": "Unknown",
          "label": "Lucas 18.10 (#4)",
          "language": "por"
        },
        {
          "reference_id": 145941,
          "content_id": 305864,
          "resource_code": "Unknown",
          "label": "Lucas 19.2 (#5)",
          "language": "por"
        },
        {
          "reference_id": 146130,
          "content_id": 306053,
          "resource_code": "Unknown",
          "label": "Lucas 19.47 (#2)",
          "language": "por"
        },
        {
          "reference_id": 146320,
          "content_id": 306243,
          "resource_code": "Unknown",
          "label": "Lucas 21.1 (#1)",
          "language": "por"
        },
        {
          "reference_id": 146493,
          "content_id": 306416,
          "resource_code": "Unknown",
          "label": "Lucas 22.2 (#1)",
          "language": "por"
        },
        {
          "reference_id": 146633,
          "content_id": 306556,
          "resource_code": "Unknown",
          "label": "Lucas 22.39 (#1)",
          "language": "por"
        },
        {
          "reference_id": 146687,
          "content_id": 306610,
          "resource_code": "Unknown",
          "label": "Lucas 22.54 (#2)",
          "language": "por"
        },
        {
          "reference_id": 146805,
          "content_id": 306728,
          "resource_code": "Unknown",
          "label": "Lucas 23.19 (#1)",
          "language": "por"
        },
        {
          "reference_id": 146827,
          "content_id": 306750,
          "resource_code": "Unknown",
          "label": "Lucas 23.26 (#3)",
          "language": "por"
        },
        {
          "reference_id": 146834,
          "content_id": 306757,
          "resource_code": "Unknown",
          "label": "Lucas 23.27 (#2)",
          "language": "por"
        },
        {
          "reference_id": 146861,
          "content_id": 306784,
          "resource_code": "Unknown",
          "label": "Lucas 23.32 (#1)",
          "language": "por"
        },
        {
          "reference_id": 146916,
          "content_id": 306839,
          "resource_code": "Unknown",
          "label": "Lucas 23.44 (#1)",
          "language": "por"
        },
        {
          "reference_id": 146949,
          "content_id": 306872,
          "resource_code": "Unknown",
          "label": "Lucas 23.51 (#1)",
          "language": "por"
        },
        {
          "reference_id": 147009,
          "content_id": 306932,
          "resource_code": "Unknown",
          "label": "Lucas 24.10 (#1)",
          "language": "por"
        },
        {
          "reference_id": 147024,
          "content_id": 306947,
          "resource_code": "Unknown",
          "label": "Lucas 24.13 (#2)",
          "language": "por"
        },
        {
          "reference_id": 169570,
          "content_id": 481803,
          "resource_code": "Unknown",
          "label": "Gênesis 2.8 (#1)",
          "language": "por"
        },
        {
          "reference_id": 169605,
          "content_id": 481838,
          "resource_code": "Unknown",
          "label": "Gênesis 2.15 (#1)",
          "language": "por"
        },
        {
          "reference_id": 169619,
          "content_id": 481852,
          "resource_code": "Unknown",
          "label": "Gênesis 2.19 (#1)",
          "language": "por"
        },
        {
          "reference_id": 169983,
          "content_id": 482216,
          "resource_code": "Unknown",
          "label": "Gênesis 6.1 (#2)",
          "language": "por"
        },
        {
          "reference_id": 170591,
          "content_id": 482824,
          "resource_code": "Unknown",
          "label": "Gênesis 11.30 (#1)",
          "language": "por"
        },
        {
          "reference_id": 170804,
          "content_id": 483037,
          "resource_code": "Unknown",
          "label": "Gênesis 14.4 (#1)",
          "language": "por"
        },
        {
          "reference_id": 171018,
          "content_id": 483251,
          "resource_code": "Unknown",
          "label": "Gênesis 16.1 (#1)",
          "language": "por"
        },
        {
          "reference_id": 173116,
          "content_id": 485349,
          "resource_code": "Unknown",
          "label": "Gênesis 31.19 (#1)",
          "language": "por"
        },
        {
          "reference_id": 173137,
          "content_id": 485370,
          "resource_code": "Unknown",
          "label": "Gênesis 31.25 (#1)",
          "language": "por"
        },
        {
          "reference_id": 173138,
          "content_id": 485371,
          "resource_code": "Unknown",
          "label": "Gênesis 31.25 (#2)",
          "language": "por"
        },
        {
          "reference_id": 173170,
          "content_id": 485403,
          "resource_code": "Unknown",
          "label": "Gênesis 31.32 (#6)",
          "language": "por"
        },
        {
          "reference_id": 173175,
          "content_id": 485408,
          "resource_code": "Unknown",
          "label": "Gênesis 31.34 (#1)",
          "language": "por"
        },
        {
          "reference_id": 173989,
          "content_id": 486222,
          "resource_code": "Unknown",
          "label": "Gênesis 39.1 (#1)",
          "language": "por"
        },
        {
          "reference_id": 174007,
          "content_id": 486240,
          "resource_code": "Unknown",
          "label": "Gênesis 39.6 (#3)",
          "language": "por"
        },
        {
          "reference_id": 174380,
          "content_id": 486613,
          "resource_code": "Unknown",
          "label": "Gênesis 42.6 (#1)",
          "language": "por"
        },
        {
          "reference_id": 175154,
          "content_id": 487387,
          "resource_code": "Unknown",
          "label": "Gênesis 48.10 (#1)",
          "language": "por"
        },
        {
          "reference_id": 187970,
          "content_id": 487662,
          "resource_code": "Unknown",
          "label": "Êxodo 1.1 (#1)",
          "language": "por"
        },
        {
          "reference_id": 188032,
          "content_id": 487724,
          "resource_code": "Unknown",
          "label": "Êxodo 1.20 (#2)",
          "language": "por"
        },
        {
          "reference_id": 188097,
          "content_id": 487789,
          "resource_code": "Unknown",
          "label": "Êxodo 2.16 (#1)",
          "language": "por"
        },
        {
          "reference_id": 188124,
          "content_id": 487816,
          "resource_code": "Unknown",
          "label": "Êxodo 2.23 (#2)",
          "language": "por"
        },
        {
          "reference_id": 188129,
          "content_id": 487821,
          "resource_code": "Unknown",
          "label": "Êxodo 3.1 (#2)",
          "language": "por"
        },
        {
          "reference_id": 188468,
          "content_id": 488160,
          "resource_code": "Unknown",
          "label": "Êxodo 6.14 (#1)",
          "language": "por"
        },
        {
          "reference_id": 188514,
          "content_id": 488206,
          "resource_code": "Unknown",
          "label": "Êxodo 7.7 (#1)",
          "language": "por"
        },
        {
          "reference_id": 188758,
          "content_id": 488450,
          "resource_code": "Unknown",
          "label": "Êxodo 9.31 (#1)",
          "language": "por"
        },
        {
          "reference_id": 188985,
          "content_id": 488677,
          "resource_code": "Unknown",
          "label": "Êxodo 13.17 (#1)",
          "language": "por"
        },
        {
          "reference_id": 189190,
          "content_id": 488882,
          "resource_code": "Unknown",
          "label": "Êxodo 16.34 (#1)",
          "language": "por"
        },
        {
          "reference_id": 161255,
          "content_id": 582989,
          "resource_code": "Unknown",
          "label": "1 Timóteo 1.5 (#1)",
          "language": "por"
        },
        {
          "reference_id": 175584,
          "content_id": 583605,
          "resource_code": "Unknown",
          "label": "Jó 1.2 (#1)",
          "language": "por"
        },
        {
          "reference_id": 175626,
          "content_id": 583647,
          "resource_code": "Unknown",
          "label": "Jó 1.14 (#1)",
          "language": "por"
        },
        {
          "reference_id": 175637,
          "content_id": 583658,
          "resource_code": "Unknown",
          "label": "Jó 1.18 (#1)",
          "language": "por"
        },
        {
          "reference_id": 175814,
          "content_id": 583835,
          "resource_code": "Unknown",
          "label": "Jó 4.12 (#2)",
          "language": "por"
        },
        {
          "reference_id": 165249,
          "content_id": 587698,
          "resource_code": "Unknown",
          "label": "Hebreus 9.1 (#1)",
          "language": "por"
        },
        {
          "reference_id": 165258,
          "content_id": 587707,
          "resource_code": "Unknown",
          "label": "Hebreus 9.2 (#5)",
          "language": "por"
        },
        {
          "reference_id": 165267,
          "content_id": 587716,
          "resource_code": "Unknown",
          "label": "Hebreus 9.4 (#1)",
          "language": "por"
        },
        {
          "reference_id": 165268,
          "content_id": 587717,
          "resource_code": "Unknown",
          "label": "Hebreus 9.4 (#2)",
          "language": "por"
        },
        {
          "reference_id": 165272,
          "content_id": 587721,
          "resource_code": "Unknown",
          "label": "Hebreus 9.4 (#6)",
          "language": "por"
        },
        {
          "reference_id": 160778,
          "content_id": 683199,
          "resource_code": "Unknown",
          "label": "1 Tessalonicenses 2.2 (#2)",
          "language": "por"
        },
        {
          "reference_id": 160847,
          "content_id": 683268,
          "resource_code": "Unknown",
          "label": "1 Tessalonicenses 2.15 (#1)",
          "language": "por"
        },
        {
          "reference_id": 153215,
          "content_id": 684590,
          "resource_code": "Unknown",
          "label": "Romanos 4.19 (#6)",
          "language": "por"
        },
        {
          "reference_id": 185372,
          "content_id": 745484,
          "resource_code": "Unknown",
          "label": "Cântico dos cânticos 3.9,10 (#1)",
          "language": "por"
        },
        {
          "reference_id": 184945,
          "content_id": 806366,
          "resource_code": "Unknown",
          "label": "Rute 1.22 (#2)",
          "language": "por"
        },
        {
          "reference_id": 184947,
          "content_id": 806368,
          "resource_code": "Unknown",
          "label": "Rute 2.1 (#1)",
          "language": "por"
        },
        {
          "reference_id": 185049,
          "content_id": 806470,
          "resource_code": "Unknown",
          "label": "Rute 3.8 (#1)",
          "language": "por"
        },
        {
          "reference_id": 185111,
          "content_id": 806532,
          "resource_code": "Unknown",
          "label": "Rute 4.7 (#1)",
          "language": "por"
        },
        {
          "reference_id": 185113,
          "content_id": 806534,
          "resource_code": "Unknown",
          "label": "Rute 4.7 (#3)",
          "language": "por"
        },
        {
          "reference_id": 168122,
          "content_id": 817276,
          "resource_code": "Unknown",
          "label": "Apocalipse 20.5 (#1)",
          "language": "por"
        }
      ]
    }
  }
]